grk/api.py
grk/cli.py
grk/config.py
grk/config_handler.py
grk/logging.py
grk/models.py
grk/runner.py
grk/utils.py
grk/core/session.py
grk_cli-0.2.2.dist-info/METADATA
grk_cli-0.2.2.dist-info/WHEEL
grk_cli-0.2.2.dist-info/entry_points.txt
grk_cli-0.2.2.dist-info/licenses/LICENSE
grk_cli-0.2.2.dist-info/RECORD
