Metadata-Version: 2.4
Name: grk-cli
Version: 0.2.2
Summary: CLI tool to call Grok LLM
Author-email: wr1 <8971152+wr1@users.noreply.github.com>
License-Expression: MIT
License-File: LICENSE
Requires-Python: <3.14,>=3.10
Requires-Dist: pydantic>=2.6
Requires-Dist: rich>=13.7.1
Requires-Dist: ruamel-yaml>=0.17
Requires-Dist: treeparse
Requires-Dist: xai-sdk
